LICENSE
MANIFEST.in
README.rst
defaults.xml
gateway.xml
setup.cfg
setup.py
./__init__.py
./defaults.py
./defaults.xml
./gateway.py
./gateway.xml
./i18n.py
./register.py
./tryton.cfg
./tests/__init__.py
./tests/test_payment.py
trytond_nereid_payment.egg-info/PKG-INFO
trytond_nereid_payment.egg-info/SOURCES.txt
trytond_nereid_payment.egg-info/dependency_links.txt
trytond_nereid_payment.egg-info/entry_points.txt
trytond_nereid_payment.egg-info/not-zip-safe
trytond_nereid_payment.egg-info/requires.txt
trytond_nereid_payment.egg-info/top_level.txt