Metadata-Version: 1.1
Name: trytond-nereid-payment
Version: 3.0.2.0
Summary: Nereid payment gateway (Deprecated)
Home-page: http://openlabs.co.in
Author: Openlabs Technologies and Consulting (P) Ltd.
Author-email: UNKNOWN
License: GPL-3
Download-URL: https://github.com/openlabs/nereid-payment
Platform: UNKNOWN
Classifier: Development Status :: 5 - Production/Stable
Classifier: Environment :: Plugins
Classifier: Intended Audience :: Developers
Classifier: Intended Audience :: Financial and Insurance Industry
Classifier: Intended Audience :: Legal Industry
Classifier: Intended Audience :: Manufacturing
Classifier: License :: OSI Approved :: GNU General Public License v3 (GPLv3)
Classifier: Natural Language :: English
Classifier: Operating System :: OS Independent
Classifier: Programming Language :: Python
Classifier: Framework :: Tryton
Classifier: Topic :: Office/Business
